server_d/__init__.py
server_d/converter.py
server_d/main.py
server_d/manage.py
server_d_pnd_123-0.0.1.dist-info/LICENSE
server_d_pnd_123-0.0.1.dist-info/METADATA
server_d_pnd_123-0.0.1.dist-info/WHEEL
server_d_pnd_123-0.0.1.dist-info/top_level.txt
server_d_pnd_123-0.0.1.dist-info/RECORD
